weng_pkgtest/__init__.py
weng_pkgtest/__version__.py
weng_pkgtest/print1.py
weng_pkgtest/print2.py
weng_pkgtest/static/.gitkeep
weng_pkgtest/templates/.gitkeep
weng_pkgtest-1.0.2.dist-info/LICENSE
weng_pkgtest-1.0.2.dist-info/METADATA
weng_pkgtest-1.0.2.dist-info/WHEEL
weng_pkgtest-1.0.2.dist-info/top_level.txt
weng_pkgtest-1.0.2.dist-info/RECORD
