Metadata-Version: 2.1
Name: weng-pkgtest
Version: 1.0.2
Summary: a python package test project
Home-page: https://github.com/MutiYouth
Author: Cheetah
Author-email: murphe@qq.com
License: Apache
Keywords: weng
Classifier: Programming Language :: Python
Classifier: Programming Language :: Python :: 3.7
Classifier: License :: OSI Approved :: Apache Software License
Classifier: Development Status :: 3 - Alpha
Classifier: Operating System :: OS Independent
Requires-Python: >=3.6
License-File: LICENSE
Requires-Dist: numpy (>=1.17.2<2.0.0)
